<?xml version="1.0" encoding="UTF-8"?>
<configuration scan="true" scanPeriod="30 seconds">

    <conversionRule conversionWord="clr"
                    converterClass="org.springframework.boot.logging.logback.ColorConverter"/>
    <conversionRule conversionWord="wEx"
                    converterClass="org.springframework.boot.logging.logback.ExtendedWhitespaceThrowableProxyConverter"/>

    <!-- ── Development profile: colored, verbose ─────────────────────── -->
    <springProfile name="!prod">
        <appender name="CONSOLE" class="ch.qos.logback.core.ConsoleAppender">
            <encoder>
                <pattern>%clr(%d{HH:mm:ss.SSS}){faint} %clr(%5p) %clr([%15.15t]){faint} %clr(%-40.40logger{39}){cyan} : %m%n%wEx</pattern>
                <charset>UTF-8</charset>
            </encoder>
        </appender>
        <logger name="az.ao.idp"                  level="DEBUG"/>
        <logger name="org.springframework.security" level="DEBUG"/>
        <logger name="org.flywaydb"                level="INFO"/>
        <root level="INFO">
            <appender-ref ref="CONSOLE"/>
        </root>
    </springProfile>

    <!-- ── Production profile: structured, timestamped ───────────────── -->
    <springProfile name="prod">
        <appender name="CONSOLE" class="ch.qos.logback.core.ConsoleAppender">
            <encoder>
                <pattern>%d{yyyy-MM-dd HH:mm:ss.SSS} %-5level [%-20thread] %-45logger{45} : %message%n%ex{full}</pattern>
                <charset>UTF-8</charset>
            </encoder>
        </appender>
        <logger name="az.ao.idp"                   level="INFO"/>
        <logger name="org.flywaydb"                level="INFO"/>
        <logger name="org.springframework.security" level="WARN"/>
        <logger name="org.hibernate.SQL"            level="WARN"/>
        <logger name="com.zaxxer.hikari"            level="WARN"/>
        <root level="WARN">
            <appender-ref ref="CONSOLE"/>
        </root>
    </springProfile>

</configuration>
